infra_event_notifier/__init__.py
infra_event_notifier/datadog_notifier.py
infra_event_notifier/jira_notifier.py
infra_event_notifier/main.py
infra_event_notifier/slack_notifier.py
infra_event_notifier/backends/__init__.py
infra_event_notifier/backends/datadog.py
infra_event_notifier/backends/jira.py
infra_event_notifier/backends/slack.py
infra_event_notifier/cli/__init__.py
infra_event_notifier/cli/command.py
infra_event_notifier/cli/datadog.py
infra_event_notifier/cli/terragrunt.py
sentry_infra_event_notifier-0.0.10.dist-info/LICENSE
sentry_infra_event_notifier-0.0.10.dist-info/METADATA
sentry_infra_event_notifier-0.0.10.dist-info/WHEEL
sentry_infra_event_notifier-0.0.10.dist-info/entry_points.txt
sentry_infra_event_notifier-0.0.10.dist-info/top_level.txt
sentry_infra_event_notifier-0.0.10.dist-info/RECORD
