Metadata-Version: 2.1
Name: sentry_infra_event_notifier
Version: 0.0.10
Summary: Package to send notifications to various backends (datadog/slack/jira)
Project-URL: Homepage, https://github.com/getsentry/infra-event-notifier
Project-URL: Issues, https://github.com/getsentry/infra-event-notifier/issues
Requires-Python: >=3.10
License-File: LICENSE
